{
  "entityType" : "ENTITY_GROUP",
  "entity" : {
    "additionalInfo" : {
      "description" : "Autogenerated Customer Users group with read-only permissions."
    },
    "configuration" : {
      "columns" : [ {
        "type" : "ENTITY_FIELD",
        "key" : "created_time",
        "sortOrder" : "DESC"
      }, {
        "type" : "ENTITY_FIELD",
        "key" : "first_name",
        "sortOrder" : "NONE"
      }, {
        "type" : "ENTITY_FIELD",
        "key" : "last_name",
        "sortOrder" : "NONE"
      }, {
        "type" : "ENTITY_FIELD",
        "key" : "email",
        "sortOrder" : "NONE"
      } ],
      "settings" : { },
      "actions" : { }
    },
    "edgeGroupAll" : false,
    "externalId" : null,
    "groupAll" : false,
    "id" : {
      "entityType" : "ENTITY_GROUP",
      "id" : "23015490-4004-11ed-b2a6-7b5ea26e454c"
    },
    "name" : "Customer Users",
    "ownerId" : {
      "entityType" : "CUSTOMER",
      "id" : "22fc4b80-4004-11ed-b2a6-7b5ea26e454c"
    },
    "type" : "USER"
  },
  "relations" : [ ],
  "attributes" : {
    "SERVER_SCOPE" : [ ]
  },
  "groupEntities" : true,
  "permissions" : [ {
    "entityGroupId" : null,
    "entityGroupType" : null,
    "roleId" : {
      "entityType" : "ROLE",
      "id" : "fac657d0-0948-11eb-b019-1b2661815418"
    },
    "tenantId" : {
      "entityType" : "TENANT",
      "id" : "02650af0-4445-11ea-bc38-336b30f475c9"
    },
    "userGroupId" : {
      "entityType" : "ENTITY_GROUP",
      "id" : "23015490-4004-11ed-b2a6-7b5ea26e454c"
    },
    "createdTime" : 1664462202978,
    "id" : {
      "entityType" : "GROUP_PERMISSION",
      "id" : "2302b420-4004-11ed-b2a6-7b5ea26e454c"
    },
    "name" : "GENERIC_[23015490-4004-11ed-b2a6-7b5ea26e454c]_[fac657d0-0948-11eb-b019-1b2661815418]",
    "public" : false
  }, {
    "entityGroupId" : {
      "entityType" : "ENTITY_GROUP",
      "id" : "2ee18d40-6a25-11eb-b7dc-cf00fa2e3e5a"
    },
    "entityGroupType" : "DASHBOARD",
    "roleId" : {
      "entityType" : "ROLE",
      "id" : "763a31c0-0949-11eb-b019-1b2661815418"
    },
    "tenantId" : {
      "entityType" : "TENANT",
      "id" : "02650af0-4445-11ea-bc38-336b30f475c9"
    },
    "userGroupId" : {
      "entityType" : "ENTITY_GROUP",
      "id" : "23015490-4004-11ed-b2a6-7b5ea26e454c"
    },
    "createdTime" : 1664463062391,
    "id" : {
      "entityType" : "GROUP_PERMISSION",
      "id" : "2342b870-4006-11ed-b2a6-7b5ea26e454c"
    },
    "name" : "GROUP_[23015490-4004-11ed-b2a6-7b5ea26e454c]_[763a31c0-0949-11eb-b019-1b2661815418]_[2ee18d40-6a25-11eb-b7dc-cf00fa2e3e5a]_[DASHBOARD]",
    "public" : false
  }, {
    "entityGroupId" : {
      "entityType" : "ENTITY_GROUP",
      "id" : "2fe25690-4005-11ed-b2a6-7b5ea26e454c"
    },
    "entityGroupType" : "DEVICE",
    "roleId" : {
      "entityType" : "ROLE",
      "id" : "763a31c0-0949-11eb-b019-1b2661815418"
    },
    "tenantId" : {
      "entityType" : "TENANT",
      "id" : "02650af0-4445-11ea-bc38-336b30f475c9"
    },
    "userGroupId" : {
      "entityType" : "ENTITY_GROUP",
      "id" : "23015490-4004-11ed-b2a6-7b5ea26e454c"
    },
    "createdTime" : 1664462680061,
    "id" : {
      "entityType" : "GROUP_PERMISSION",
      "id" : "3f5fcad0-4005-11ed-b2a6-7b5ea26e454c"
    },
    "name" : "GROUP_[23015490-4004-11ed-b2a6-7b5ea26e454c]_[763a31c0-0949-11eb-b019-1b2661815418]_[2fe25690-4005-11ed-b2a6-7b5ea26e454c]_[DEVICE]",
    "public" : false
  }, {
    "entityGroupId" : {
      "entityType" : "ENTITY_GROUP",
      "id" : "ee3f3500-4004-11ed-b2a6-7b5ea26e454c"
    },
    "entityGroupType" : "ASSET",
    "roleId" : {
      "entityType" : "ROLE",
      "id" : "763a31c0-0949-11eb-b019-1b2661815418"
    },
    "tenantId" : {
      "entityType" : "TENANT",
      "id" : "02650af0-4445-11ea-bc38-336b30f475c9"
    },
    "userGroupId" : {
      "entityType" : "ENTITY_GROUP",
      "id" : "23015490-4004-11ed-b2a6-7b5ea26e454c"
    },
    "createdTime" : 1664462558830,
    "id" : {
      "entityType" : "GROUP_PERMISSION",
      "id" : "f71d68e0-4004-11ed-b2a6-7b5ea26e454c"
    },
    "name" : "GROUP_[23015490-4004-11ed-b2a6-7b5ea26e454c]_[763a31c0-0949-11eb-b019-1b2661815418]_[ee3f3500-4004-11ed-b2a6-7b5ea26e454c]_[ASSET]",
    "public" : false
  } ]
}