{
  "entityType" : "ENTITY_GROUP",
  "entity" : {
    "additionalInfo" : {
      "description" : "Autogenerated Customer Administrators group with all permissions."
    },
    "configuration" : {
      "columns" : [ {
        "type" : "ENTITY_FIELD",
        "key" : "created_time",
        "sortOrder" : "DESC"
      }, {
        "type" : "ENTITY_FIELD",
        "key" : "first_name",
        "sortOrder" : "NONE"
      }, {
        "type" : "ENTITY_FIELD",
        "key" : "last_name",
        "sortOrder" : "NONE"
      }, {
        "type" : "ENTITY_FIELD",
        "key" : "email",
        "sortOrder" : "NONE"
      } ],
      "settings" : { },
      "actions" : { }
    },
    "edgeGroupAll" : false,
    "externalId" : null,
    "groupAll" : false,
    "id" : {
      "entityType" : "ENTITY_GROUP",
      "id" : "40d5b2c0-8a7b-11ec-9770-eb90561c60d1"
    },
    "name" : "Customer Administrators",
    "ownerId" : {
      "entityType" : "CUSTOMER",
      "id" : "40c97dc0-8a7b-11ec-9770-eb90561c60d1"
    },
    "type" : "USER"
  },
  "relations" : [ ],
  "attributes" : {
    "SERVER_SCOPE" : [ ]
  },
  "groupEntities" : true,
  "permissions" : [ {
    "entityGroupId" : null,
    "entityGroupType" : null,
    "roleId" : {
      "entityType" : "ROLE",
      "id" : "faca0150-0948-11eb-b019-1b2661815418"
    },
    "tenantId" : {
      "entityType" : "TENANT",
      "id" : "02650af0-4445-11ea-bc38-336b30f475c9"
    },
    "userGroupId" : {
      "entityType" : "ENTITY_GROUP",
      "id" : "40d5b2c0-8a7b-11ec-9770-eb90561c60d1"
    },
    "createdTime" : 1644502251507,
    "id" : {
      "entityType" : "GROUP_PERMISSION",
      "id" : "40d6c430-8a7b-11ec-9770-eb90561c60d1"
    },
    "name" : "GENERIC_[40d5b2c0-8a7b-11ec-9770-eb90561c60d1]_[faca0150-0948-11eb-b019-1b2661815418]",
    "public" : false
  } ]
}